src/__init__.py
src/gateinterface.py
src/gateobjcreate.py
src/parse.py
src/simulator.py
logicsim-0.0.1.dist-info/METADATA
logicsim-0.0.1.dist-info/WHEEL
logicsim-0.0.1.dist-info/licenses/LICENSE
logicsim-0.0.1.dist-info/RECORD
